Workbook

Sheet Raw Dataset
A1: 🛒 E-Commerce Sales Dataset — Data Analytics Teaching Sample
A2: Use this dataset to practice: sorting, filtering, pivot tables, VLOOKUP/XLOOKUP, charts, and statistical functions.
A3: Order ID | B3: Customer Name | C3: Region | D3: Product Category | E3: Product Name | F3: Units Sold | G3: Unit Price ($) | H3: Revenue ($) | I3: Discount (%) | J3: Net Revenue ($) | K3: Order Date | L3: Delivery Days
A4: ORD-1001 | B4: Liam Ndungu | C4: East | D4: Electronics | E4: Laptop | F4: 9 | G4: 850 | H4: =F4*G4 -> 7650 | I4: 5 | J4: =H4*(1-I4/100) -> 7267.5 | K4: 2024-04-05 | L4: 10
A5: ORD-1002 | B5: David Omondi | C5: West | D5: Electronics | E5: Smartwatch | F5: 14 | G5: 280 | H5: =F5*G5 -> 3920 | I5: 0 | J5: =H5*(1-I5/100) -> 3920 | K5: 2024-01-03 | L5: 10
A6: ORD-1003 | B6: Liam Ndungu | C6: South | D6: Sports | E6: Yoga Mat | F6: 18 | G6: 45 | H6: =F6*G6 -> 810 | I6: 5 | J6: =H6*(1-I6/100) -> 769.5 | K6: 2024-12-21 | L6: 5
A7: ORD-1004 | B7: Grace Njeri | C7: North | D7: Books | E7: Statistics Guide | F7: 9 | G7: 29 | H7: =F7*G7 -> 261 | I7: 0 | J7: =H7*(1-I7/100) -> 261 | K7: 2024-03-23 | L7: 6
A8: ORD-1005 | B8: Bob Mutua | C8: North | D8: Clothing | E8: Jeans | F8: 11 | G8: 60 | H8: =F8*G8 -> 660 | I8: 0 | J8: =H8*(1-I8/100) -> 660 | K8: 2024-02-13 | L8: 7
A9: ORD-1006 | B9: Olivia Chebet | C9: South | D9: Sports | E9: Dumbbell Set | F9: 2 | G9: 120 | H9: =F9*G9 -> 240 | I9: 15 | J9: =H9*(1-I9/100) -> 204 | K9: 2024-09-04 | L9: 3
A10: ORD-1007 | B10: Liam Ndungu | C10: East | D10: Sports | E10: Dumbbell Set | F10: 20 | G10: 120 | H10: =F10*G10 -> 2400 | I10: 10 | J10: =H10*(1-I10/100) -> 2160 | K10: 2024-10-07 | L10: 2
A11: ORD-1008 | B11: Eve Kamau | C11: South | D11: Clothing | E11: Jacket | F11: 3 | G11: 110 | H11: =F11*G11 -> 330 | I11: 5 | J11: =H11*(1-I11/100) -> 313.5 | K11: 2024-02-13 | L11: 7
A12: ORD-1009 | B12: Liam Ndungu | C12: East | D12: Clothing | E12: Jacket | F12: 12 | G12: 110 | H12: =F12*G12 -> 1320 | I12: 5 | J12: =H12*(1-I12/100) -> 1254 | K12: 2024-11-09 | L12: 4
A13: ORD-1010 | B13: Olivia Chebet | C13: West | D13: Sports | E13: Running Shoes | F13: 6 | G13: 100 | H13: =F13*G13 -> 600 | I13: 15 | J13: =H13*(1-I13/100) -> 510 | K13: 2024-07-09 | L13: 7
A14: ORD-1011 | B14: Bob Mutua | C14: West | D14: Electronics | E14: Smartphone | F14: 2 | G14: 620 | H14: =F14*G14 -> 1240 | I14: 10 | J14: =H14*(1-I14/100) -> 1116 | K14: 2024-07-09 | L14: 7
A15: ORD-1012 | B15: Carol Wanjiku | C15: West | D15: Clothing | E15: Dress | F15: 13 | G15: 75 | H15: =F15*G15 -> 975 | I15: 15 | J15: =H15*(1-I15/100) -> 828.75 | K15: 2024-03-09 | L15: 10
... A103: ORD-1100 | B103: Alice Johnson | C103: West | D103: Electronics | E103: Headphones | F103: 15 | G103: 150 | H103: =F103*G103 -> 2250 | I103: 20 | J103: =H103*(1-I103/100) -> 1800 | K103: 2024-08-10 | L103: 6

Sheet Summary Statistics
A1: 📊 Summary Statistics — Practice Statistical Functions
A3: Metric | B3: Value | C3: Formula Used | E3: Region | F3: Total Revenue ($)
A4: Total Orders | B4: =COUNTA('Raw Dataset'!A4:A103) -> 100 | C4: COUNTA( range ) | E4: East | F4: =SUMIF('Raw Dataset'!C4:C103,E4,'Raw Dataset'!H4:H103) -> 39751
A5: Total Revenue ($) | B5: =SUM('Raw Dataset'!H4:H103) -> 124021 | C5: SUM( range ) | E5: West | F5: =SUMIF('Raw Dataset'!C4:C103,E5,'Raw Dataset'!H4:H103) -> 29231
A6: Total Net Revenue ($) | B6: =SUM('Raw Dataset'!J4:J103) -> 112780.4 | C6: SUM( range ) | E6: North | F6: =SUMIF('Raw Dataset'!C4:C103,E6,'Raw Dataset'!H4:H103) -> 44630
A7: Avg Order Value ($) | B7: =AVERAGE('Raw Dataset'!H4:H103) -> 1240.21 | C7: AVERAGE( range ) | E7: South | F7: =SUMIF('Raw Dataset'!C4:C103,E7,'Raw Dataset'!H4:H103) -> 10409
A8: Max Single Revenue ($) | B8: =MAX('Raw Dataset'!H4:H103) -> 15300 | C8: MAX( range )
A9: Min Single Revenue ($) | B9: =MIN('Raw Dataset'!H4:H103) -> 30 | C9: MIN( range )
A10: Avg Discount (%) | B10: =AVERAGE('Raw Dataset'!I4:I103) -> 9.85 | C10: AVERAGE( range )
A11: Avg Delivery Days | B11: =AVERAGE('Raw Dataset'!L4:L103) -> 6.35 | C11: AVERAGE( range )
A12: Median Revenue ($) | B12: =MEDIAN('Raw Dataset'!H4:H103) -> 555.5 | C12: MEDIAN( range )
A13: Std Dev Revenue ($) | B13: =STDEV('Raw Dataset'!H4:H103) -> 2102.1898 | C13: STDEV( range )

Sheet Exercises
A1: 📝 Student Exercises — Data Analytics with Excel
A3: # | B3: Exercise | C3: Hint / Function to Use | D3: Your Answer
A4: ── BEGINNER LEVEL ──
A5: 1 | B5: Sort the Raw Dataset by Revenue (highest to lowest). Which product generated the most revenue? | C5: Sort & Filter ribbon
A6: 2 | B6: Use AutoFilter to show only orders from the 'East' region. How many orders are there? | C6: AutoFilter
A7: 3 | B7: Use COUNTIF to count how many orders belong to each Product Category. | C7: COUNTIF(range, criteria)
A8: 4 | B8: Calculate the total revenue for 'Electronics' using SUMIF. | C8: SUMIF(range, criteria, sum_range)
A9: 5 | B9: Find the customer who placed the highest-value single order using MAX and INDEX/MATCH. | C9: INDEX + MATCH functions
A10: ── INTERMEDIATE LEVEL ──
A11: 6 | B11: Create a Pivot Table showing total Net Revenue by Region and Category. | C11: Insert Pivot Table
A12: 7 | B12: Use AVERAGEIF to find the average discount given in the 'West' region. | C12: AVERAGEIF(range, criteria, avg_range)
A13: 8 | B13: Add a new column 'Profit Tier' using IF: High (>$500), Medium ($100-$500), Low (<$100). | C13: IF(H>500,"High",IF(H>=100,"Medium","Low"))
A14: 9 | B14: Create a Bar Chart comparing total revenue across the 4 regions. | C14: Insert Bar Chart
A15: 10 | B15: Use VLOOKUP or XLOOKUP to build a product lookup table by Order ID. | C15: XLOOKUP(lookup, array, return)
A16: ── ADVANCED LEVEL ──
A17: 11 | B17: Calculate the month-over-month revenue trend using TEXT and SUMIF on the Order Date column. | C17: TEXT(date,YYYY-MM) + SUMIF
A18: 12 | B18: Use conditional formatting to highlight the top 10 orders by revenue in green. | C18: Conditional Formatting Top 10
A19: 13 | B19: Build a dynamic dashboard: slicers + pivot chart showing sales by category over time. | C19: PivotChart + Slicers
A20: 14 | B20: Compute correlation between Units Sold and Discount (%) using CORREL. What does it mean? | C20: CORREL(array1, array2)
A21: 15 | B21: Identify duplicate customer names using COUNTIF and flag repeat buyers. | C21: COUNTIF for duplicate names

Sheet Data Dictionary
A1: 📖 Data Dictionary — Understanding the Dataset
A3: Column Name | B3: Data Type | C3: Description | D3: Example Value | E3: Analytics Use Case
A4: Order ID | B4: Text | C4: Unique identifier for each order | D4: ORD-1001 | E4: Lookup, VLOOKUP/XLOOKUP
A5: Customer Name | B5: Text | C5: Full name of the customer | D5: Alice Johnson | E5: COUNTIF for repeat buyers
A6: Region | B6: Text | C6: Sales region (East/West/North/South) | D6: East | E6: SUMIF, Pivot Tables, Charts
A7: Product Category | B7: Text | C7: Broad category of product | D7: Electronics | E7: Grouping, filtering
A8: Product Name | B8: Text | C8: Specific product sold | D8: Laptop | E8: COUNTIF, frequency analysis
A9: Units Sold | B9: Number | C9: Quantity of units in the order | D9: 5 | E9: SUM, AVERAGE, CORREL
A10: Unit Price ($) | B10: Currency | C10: Price per single unit | D10: 850.00 | E10: Revenue calculations
A11: Revenue ($) | B11: Formula | C11: Units Sold × Unit Price | D11: 4,250.00 | E11: SUM, MAX, MIN, MEDIAN
A12: Discount (%) | B12: Number | C12: Percentage discount applied | D12: 10 | E12: AVERAGEIF, correlation
A13: Net Revenue ($) | B13: Formula | C13: Revenue after discount applied | D13: 3,825.00 | E13: Profitability analysis
A14: Order Date | B14: Date | C14: Date the order was placed | D14: 2024-03-15 | E14: Time-series, MONTH(), TEXT()
A15: Delivery Days | B15: Number | C15: Days taken to deliver the order | D15: 5 | E15: AVERAGE, performance KPI
